ifri_mini_ml_lib/__init__.py
ifri_mini_ml_lib/association_rules/__init__.py
ifri_mini_ml_lib/association_rules/apriori.py
ifri_mini_ml_lib/association_rules/eclat.py
ifri_mini_ml_lib/association_rules/fp_growth.py
ifri_mini_ml_lib/association_rules/metrics.py
ifri_mini_ml_lib/association_rules/utils.py
ifri_mini_ml_lib/classification/__init__.py
ifri_mini_ml_lib/classification/decision_tree.py
ifri_mini_ml_lib/classification/knn.py
ifri_mini_ml_lib/classification/logistic_regression.py
ifri_mini_ml_lib/clustering/__init__.py
ifri_mini_ml_lib/clustering/dbscan.py
ifri_mini_ml_lib/clustering/hierarchical.py
ifri_mini_ml_lib/clustering/kmeans.py
ifri_mini_ml_lib/clustering/utils.py
ifri_mini_ml_lib/metrics/__init__.py
ifri_mini_ml_lib/metrics/bias_evaluation.py
ifri_mini_ml_lib/metrics/evaluation_metrics.py
ifri_mini_ml_lib/model_selection/__init__.py
ifri_mini_ml_lib/model_selection/bagging.py
ifri_mini_ml_lib/model_selection/bayesian_searchCV.py
ifri_mini_ml_lib/model_selection/cross_validation.py
ifri_mini_ml_lib/model_selection/grid_searchCV.py
ifri_mini_ml_lib/model_selection/random_searchCV.py
ifri_mini_ml_lib/model_selection/utils.py
ifri_mini_ml_lib/neural_networks/__init__.py
ifri_mini_ml_lib/neural_networks/mlp_classifier.py
ifri_mini_ml_lib/neural_networks/mlp_regressor.py
ifri_mini_ml_lib/preprocessing/__init__.py
ifri_mini_ml_lib/preprocessing/dimensionality_reduction/__init__.py
ifri_mini_ml_lib/preprocessing/dimensionality_reduction/pca.py
ifri_mini_ml_lib/preprocessing/dimensionality_reduction/t_sne.py
ifri_mini_ml_lib/preprocessing/preparation/__init__.py
ifri_mini_ml_lib/preprocessing/preparation/categorical_encoder.py
ifri_mini_ml_lib/preprocessing/preparation/data_splitter.py
ifri_mini_ml_lib/preprocessing/preparation/min_max_scaler.py
ifri_mini_ml_lib/preprocessing/preparation/missing_value_handler.py
ifri_mini_ml_lib/preprocessing/preparation/standard_scaler.py
ifri_mini_ml_lib/regression/__init__.py
ifri_mini_ml_lib/regression/linear.py
ifri_mini_ml_lib-0.2.1.dist-info/licenses/LICENSE
ifri_mini_ml_lib-0.2.1.dist-info/METADATA
ifri_mini_ml_lib-0.2.1.dist-info/WHEEL
ifri_mini_ml_lib-0.2.1.dist-info/top_level.txt
ifri_mini_ml_lib-0.2.1.dist-info/RECORD
