Metadata-Version: 2.4
Name: ifri_mini_ml_lib
Version: 0.2.1
Summary: A lightweight machine learning library built from scratch by IFRI IA students
Home-page: https://github.com/IFRI-AI-Classes/ifri_mini_ml_lib
Author: IFRI IA Students
Keywords: machine-learning education from-scratch ml-library ifri ai
Classifier: Programming Language :: Python :: 3
Classifier: License :: OSI Approved :: MIT License
Classifier: Operating System :: OS Independent
Classifier: Topic :: Scientific/Engineering :: Artificial Intelligence
Requires-Python: >=3.9
License-File: LICENSE
Requires-Dist: numpy
Requires-Dist: pandas
Requires-Dist: scipy
Requires-Dist: matplotlib
Requires-Dist: cvxpy
Provides-Extra: dev
Requires-Dist: pytest; extra == "dev"
Requires-Dist: pytest-cov; extra == "dev"
Requires-Dist: black; extra == "dev"
Requires-Dist: isort; extra == "dev"
Requires-Dist: flake8; extra == "dev"
Provides-Extra: docs
Requires-Dist: pdoc; extra == "docs"
Dynamic: author
Dynamic: classifier
Dynamic: description
Dynamic: description-content-type
Dynamic: home-page
Dynamic: keywords
Dynamic: license-file
Dynamic: provides-extra
Dynamic: requires-dist
Dynamic: requires-python
Dynamic: summary
